TableCity/__init__.py
TableCity/main.py
TableCity/Connection_mysql_db/__init__.py
TableCity/Connection_mysql_db/connection_mysql_db.py
TableCity/Tables/BaseModel.py
TableCity/Tables/City.py
TableCity/Tables/Country.py
TableCity/Tables/Density.py
TableCity/Tables/__init__.py
TableCity-0.0.1.dist-info/LICENSE
TableCity-0.0.1.dist-info/METADATA
TableCity-0.0.1.dist-info/WHEEL
TableCity-0.0.1.dist-info/top_level.txt
TableCity-0.0.1.dist-info/RECORD
